cpu_quota/__init__.py
cpu_quota/core.py
cpu_quota-0.1.0.dist-info/METADATA
cpu_quota-0.1.0.dist-info/WHEEL
cpu_quota-0.1.0.dist-info/entry_points.txt
cpu_quota-0.1.0.dist-info/licenses/LICENSE
cpu_quota-0.1.0.dist-info/RECORD
