Metadata-Version: 2.4
Name: cpu-quota
Version: 0.1.0
Summary: Determine the actual number of CPUs available based on systemd resource limits - more accurate than nproc in shared systems with CPU quotas
Project-URL: Homepage, https://github.com/mpinb/howto-cpu-quota
Project-URL: Repository, https://github.com/mpinb/howto-cpu-quota
Project-URL: Issues, https://github.com/mpinb/howto-cpu-quota/issues
Author-email: Omar Valerio <omar.valerio@mpinb.mpg.de>
License: MIT
License-File: LICENSE
Keywords: cpu,nproc,parallel,quota,resource-limits,shared-computing,systemd
Classifier: Development Status :: 4 - Beta
Classifier: Intended Audience :: Developers
Classifier: Intended Audience :: System Administrators
Classifier: License :: OSI Approved :: MIT License
Classifier: Operating System :: POSIX :: Linux
Classifier: Programming Language :: Python :: 3
Classifier: Programming Language :: Python :: 3.8
Classifier: Programming Language :: Python :: 3.9
Classifier: Programming Language :: Python :: 3.10
Classifier: Programming Language :: Python :: 3.11
Classifier: Programming Language :: Python :: 3.12
Classifier: Topic :: System :: Monitoring
Classifier: Topic :: System :: Systems Administration
Requires-Python: >=3.8
